{
  "code": "4w1h_006",
  "name": "多功能義大利麵鍋",
  "brand": "燕三条キッチン研究所",
  "desc": "一般的的義大利麵鍋通常是深桶型，可以裝滿大量的水。然而，若將「長條義大利麵橫放著煮」這個想法轉換90度，就能用少量的水也能煮熟，並且成為一個能同時完成三種功能的烹飪器具。",
  "spec": [
    {
      "label": "品名",
      "value": "多功能義大利麵鍋"
    },
    {
      "label": "定價",
      "value": "7,700日圓（含稅700日圓）"
    },
    {
      "label": "型號",
      "value": "4w1h_006"
    },
    {
      "label": "尺寸",
      "value": "約34×23×高 10.2cm"
    },
    {
      "label": "材質",
      "value": "本體/複合材質  \n（鋁合金不鏽鋼（鉻18％））（底部厚度 約2.0mm）  \n把手・蓋子旋鈕/酚醛樹脂  \n蓋子/不鏽鋼"
    },
    {
      "label": "重量",
      "value": "約1,380公克"
    },
    {
      "label": "滿水容量",
      "value": "約3.8公升"
    },
    {
      "label": "顏色",
      "value": "黑色（本體）"
    },
    {
      "label": "原產國",
      "value": "日本"
    },
    {
      "label": "其他",
      "value": "適用於IH爐與瓦斯爐"
    }
  ],
  "wh": [
    {
      "title": "Who",
      "text": "無論是一個人、夫妻，還是有小孩的家庭。"
    },
    {
      "title": "When",
      "text": "有時候，我們只想快速解決午餐或晚餐。"
    },
    {
      "title": "What",
      "text": "在這時候，簡單方便的義大利麵就派上用場了。"
    },
    {
      "title": "how",
      "text": "但是倒水的時候和後續清理的負擔相當沉重。"
    },
    {
      "title": "Why",
      "text": "能不能用一個鍋子就完成煮麵、瀝水、炒麵的所有步驟呢？"
    }
  ],
  "images": {
    "main": {
      "filename": "uncle-benny-4w1h_006_mainimg.webp",
      "url": null,
      "alt": "4w1h_006",
      "status": "ok"
    },
    "hero": {
      "filename": "uncle-benny-4w1h_006_hero.webp",
      "url": null,
      "alt": "4w1h_006",
      "status": "ok"
    },
    "thema": {
      "filename": "uncle-benny-4w1h_006_thema.webp",
      "url": null,
      "alt": "最快速地將義大利麵端上餐桌。",
      "status": "ok"
    },
    "slides": [
      {
        "filename": "uncle-benny-4w1h_006__pasta-pan_slide_01.webp",
        "url": null,
        "alt": "",
        "status": "ok"
      },
      {
        "filename": "uncle-benny-4w1h_006__pasta-pan_slide_02.webp",
        "url": null,
        "alt": "",
        "status": "ok"
      },
      {
        "filename": "uncle-benny-4w1h_006__pasta-pan_slide_03.webp",
        "url": null,
        "alt": "",
        "status": "ok"
      }
    ]
  },
  "features": [
    {
      "filename": "uncle-benny-4w1h_006__pasta-pan_feature_01.webp",
      "alt": "要用最少的水煮長條義大利麵該怎麼做呢？",
      "title": "要用最少的水煮長條義大利麵該怎麼做呢？",
      "desc": "煮義大利麵的第一個挑戰，就是要用深鍋煮大量的水。無論是加水還是倒水，都是一項不小的力氣活。因此，我們思考了「如何用最少的水煮麵？」而設計出這個形狀。將義大利麵從直立投入改為橫放平躺著煮，就不需要深鍋了。水量也可以減少，因此能更快地煮沸。（可煮的義大利麵量約為500克）",
      "youtube": null
    },
    {
      "filename": "uncle-benny-4w1h_006__pasta-pan_feature_02.webp",
      "alt": "波形縫隙設計，瀝水效果極佳，不需要濾網。",
      "title": "波形縫隙設計，瀝水效果極佳，不需要濾網。",
      "desc": "意外地費時的瀝水作業。如果可以的話，沒有濾網、一步到位是理想的選擇。實現這一點的是蓋子上的波形縫隙。這些縫隙讓湯水不會溢出，同時不會阻擋水流，並且凹槽設計的把手可以固定蓋子，只需傾斜鍋子就能完成瀝水。為了徹底瀝乾湯水，鍋身特別設計了引導水流的傾斜角度。",
      "youtube": null
    },
    {
      "filename": null,
      "alt": "",
      "title": "順暢完成煮、瀝水、炒的所有步驟。",
      "desc": "煮義大利麵時，每個步驟都需要不同的工具，常常會增加大量的清洗工作。因此，我們設計了這款多功能義大利麵鍋，讓煮麵到炒麵的所有步驟都能在一個鍋子裡完成。鍋內側經過氟素塗層處理，旨在大幅減少烹飪和清理的麻煩。",
      "youtube": "https://www.youtube.com/embed/ZjaG08dg_pY"
    },
    {
      "filename": "uncle-benny-4w1h_006__pasta-pan_feature_04.webp",
      "alt": "從今以後，鍋子的把手就是蓋子的固定位置。",
      "title": "從今以後，鍋子的把手就是蓋子的固定位置。",
      "desc": "煮沸後的麻煩就是蓋子的處理。如果不知道該把蓋子放哪裡，那就順手插入鍋子的把手上吧。這款設計可以在約80度和約110度兩個角度立起，讓煮麵時水滴不容易附著。",
      "youtube": null
    },
    {
      "filename": "uncle-benny-4w1h_006__pasta-pan_feature_05.webp",
      "alt": "不僅僅是義大利麵，燙青菜也能輕鬆瀝乾。",
      "title": "不僅僅是義大利麵，燙青菜也能輕鬆瀝乾。",
      "desc": "這款淺型鍋導熱均勻，火力容易穿透，煮蔬菜時也非常好用。像是玉米和蘆筍這類較長的蔬菜也能輕鬆處理。除了麵條之外，還可以從波形開口的另一側快速瀝水。",
      "youtube": null
    }
  ],
  "notices": [],
  "hashtags": "#橫向煮麵 #少量水煮 #瀝水超方便 #免濾網 #一鍋料理 #免找鍋蓋放置處 #溫野菜也行"
}